fateful-0.4.0.dist-info/METADATA
fateful-0.4.0.dist-info/WHEEL
fateful/__init__.py
fateful/container.py
fateful/http.py
fateful/json.py
fateful/monad/__init__.py
fateful/monad/async_result.py
fateful/monad/container.py
fateful/monad/effect.py
fateful/monad/func.py
fateful/monad/option.py
fateful/monad/result.py
fateful/py.typed.py
fateful-0.4.0.dist-info/RECORD
