Metadata-Version: 2.1
Name: fateful
Version: 0.4.0
Summary: rusty Option and Result container for python. Ready for pattern matching and asyncio
Author-Email: Marco <cram@hotmail.fr>
License: MIT
Requires-Python: >=3.10
Requires-Dist: pampy>=0.3.0
Requires-Dist: aiohttp>=3.8.4; extra == "http"
Requires-Dist: orjson; extra == "orjson"
Requires-Dist: fateful[http,orjson]; extra == "all"
Provides-Extra: http
Provides-Extra: orjson
Provides-Extra: all
